dojo_sdk_client/__about__.py
dojo_sdk_client/__init__.py
dojo_sdk_client/__main__.py
dojo_sdk_client/base_dojo_client.py
dojo_sdk_client/dojo_eval_client.py
dojo_sdk_client/multi_turn_env.py
dojo_sdk_client/types.py
dojo_sdk_client/agents/__init__.py
dojo_sdk_client/agents/anthropic_cua.py
dojo_sdk_client/agents/base_agent.py
dojo_sdk_client/agents/base_tool.py
dojo_sdk_client/agents/basic_cua.py
dojo_sdk_client/agents/computer_use_tool.py
dojo_sdk_client/agents/example_agent.py
dojo_sdk_client/agents/mcp_use_tool.py
dojo_sdk_client/agents/prompts.py
dojo_sdk_client/agents/seed_cua.py
dojo_sdk_client/agents/token_tracker.py
dojo_sdk_client/agents/utils/response_processor.py
dojo_sdk_client/engines/__init__.py
dojo_sdk_client/engines/browserController.py
dojo_sdk_client/engines/browserbase_engine.py
dojo_sdk_client/engines/detect_engine.py
dojo_sdk_client/engines/dojo_engine.py
dojo_sdk_client/engines/engine.py
dojo_sdk_client/telemetry/dojo_telemetry.py
dojo_sdk_client/telemetry/types.py
dojo_sdk_client/utils/__init__.py
dojo_sdk_client/utils/bench.py
dojo_sdk_client/utils/utils.py
dojo_sdk_client-0.1.36.dist-info/METADATA
dojo_sdk_client-0.1.36.dist-info/WHEEL
dojo_sdk_client-0.1.36.dist-info/RECORD
